illiterally/__init__.py
illiterally/block.py
illiterally/cli.py
illiterally/entry_points.py
illiterally/illiterally.py
illiterally/log.py
illiterally/state.py
illiterally/utils.py
illiterally-2024.0.8.post2.dist-info/LICENSE
illiterally-2024.0.8.post2.dist-info/METADATA
illiterally-2024.0.8.post2.dist-info/WHEEL
illiterally-2024.0.8.post2.dist-info/entry_points.txt
illiterally-2024.0.8.post2.dist-info/top_level.txt
illiterally-2024.0.8.post2.dist-info/RECORD
