Metadata-Version: 2.1
Name: illiterally
Version: 2024.0.8.post2
Summary: Simple literate programming tool
Author-email: James Gregson <james.gregson@gmail.com>
Maintainer-email: James Gregson <james.gregson@gmail.com>
License: Copyright 2024 James Gregson
Project-URL: Homepage, https://github.com/jamesgregson/illiterally
Project-URL: Documentation, https://github.com/jamesgregson/illiterally
Project-URL: Repository, https://github.com/jamesgregson/illiterally.git
Keywords: literate programming,documentation,emoji
Classifier: Development Status :: 4 - Beta
Classifier: Programming Language :: Python
Requires-Python: >=3.9
License-File: LICENSE
Requires-Dist: python-slugify
Requires-Dist: jinja2
Requires-Dist: emoji
Requires-Dist: pytest
